{
  "character": {
    "name": "Anh Khôi",
    "level": 15,
    "xp": 450,
    "xp_to_next_level": 800,
    "hp": 120,
    "max_hp": 150,
    "gold": 350,
    "dex": 25,
    "int": 18,
    "luk": 22,
    "available_points": 3,
    "unlocked_achievements": [
      "BuocDiDauTien",
      "HocVienXuatSac",
      "ChamChiCanCu"
    ],
    "inventory": [
      {
        "name": "Potion of Focus",
        "description": "Increases concentration for studying",
        "category": "Consumable",
        "rarity": "RARE",
        "price": 50,
        "icon": "potion_focus.png",
        "consumable": true,
        "passive": false,
        "on_use_effect": {
          "xp": 5,
          "int": 2
        }
      },
      {
        "name": "Ancient Codex",
        "description": "A mystical book that enhances learning",
        "category": "Equipment",
        "rarity": "EPIC",
        "price": 200,
        "icon": "ancient_book.png",
        "consumable": false,
        "passive": true,
        "on_use_effect": {
          "int": 8,
          "xp": 15,
          "hp": 10
        }
      }
    ],
    "equipment": [
      {
        "name": "Ancient Codex",
        "description": "A mystical book that enhances learning",
        "category": "Equipment",
        "rarity": "EPIC",
        "price": 200,
        "icon": "ancient_book.png",
        "consumable": false,
        "passive": true,
        "on_use_effect": {
          "int": 8,
          "xp": 15,
          "hp": 10
        }
      }
    ]
  },
  "analytics": {
    "session_history": [
      {
        "session_id": "demo_session_0",
        "goal": "Study Session Day 1",
        "status": "Finished",
        "start_time": "2025-06-18T00:01:45.287448",
        "end_time": "2025-06-18T02:35:45.287448",
        "rank": "C",
        "duration_seconds": 9240.0,
        "linked_quests_data": [
          {
            "quest_id": "quest_f7283c01-6181-422f-8175-7e0d52cacc88",
            "description": "Task 1 for Day 1",
            "difficulty": 3,
            "is_completed": false
          },
          {
            "quest_id": "quest_e5f10789-d408-48f9-a502-3869719aa80c",
            "description": "Task 2 for Day 1",
            "difficulty": 3,
            "is_completed": true
          }
        ]
      },
      {
        "session_id": "demo_session_1",
        "goal": "Study Session Day 2",
        "status": "Finished",
        "start_time": "2025-06-19T00:01:45.287448",
        "end_time": "2025-06-19T02:10:45.287448",
        "rank": "A",
        "duration_seconds": 7740.0,
        "linked_quests_data": [
          {
            "quest_id": "quest_5db03694-81c2-4559-b92a-8b051dc2bd3f",
            "description": "Task 1 for Day 2",
            "difficulty": 3,
            "is_completed": true
          },
          {
            "quest_id": "quest_051eab1a-cf6c-4ac8-889d-c82a1188b851",
            "description": "Task 2 for Day 2",
            "difficulty": 1,
            "is_completed": false
          },
          {
            "quest_id": "quest_515da68b-d6ab-45c9-b834-1ee20121f8dd",
            "description": "Task 3 for Day 2",
            "difficulty": 2,
            "is_completed": true
          }
        ]
      },
      {
        "session_id": "demo_session_2",
        "goal": "Study Session Day 3",
        "status": "Finished",
        "start_time": "2025-06-20T00:01:45.287448",
        "end_time": "2025-06-20T02:41:45.287448",
        "rank": "C",
        "duration_seconds": 9600.0,
        "linked_quests_data": [
          {
            "quest_id": "quest_72b90a30-a3cf-4586-8913-112c5e7a23e5",
            "description": "Task 1 for Day 3",
            "difficulty": 2,
            "is_completed": false
          },
          {
            "quest_id": "quest_8d16fcac-23a9-4954-8959-bfe5002c23f7",
            "description": "Task 2 for Day 3",
            "difficulty": 1,
            "is_completed": true
          }
        ]
      },
      {
        "session_id": "demo_session_3",
        "goal": "Study Session Day 4",
        "status": "Finished",
        "start_time": "2025-06-21T00:01:45.287448",
        "end_time": "2025-06-21T02:39:45.287448",
        "rank": "A",
        "duration_seconds": 9480.0,
        "linked_quests_data": [
          {
            "quest_id": "quest_9e06a618-041d-4901-b832-9715635b4416",
            "description": "Task 1 for Day 4",
            "difficulty": 2,
            "is_completed": true
          },
          {
            "quest_id": "quest_185fd19f-3966-4964-8cad-b2736e0367b4",
            "description": "Task 2 for Day 4",
            "difficulty": 1,
            "is_completed": true
          }
        ]
      },
      {
        "session_id": "demo_session_4",
        "goal": "Study Session Day 5",
        "status": "Finished",
        "start_time": "2025-06-22T00:01:45.287448",
        "end_time": "2025-06-22T02:44:45.287448",
        "rank": "C",
        "duration_seconds": 9780.0,
        "linked_quests_data": [
          {
            "quest_id": "quest_84ad0065-9876-4131-93a9-101c24c95611",
            "description": "Task 1 for Day 5",
            "difficulty": 1,
            "is_completed": true
          },
          {
            "quest_id": "quest_5faba3c6-e46c-4fb3-b6a0-f357a0535c78",
            "description": "Task 2 for Day 5",
            "difficulty": 2,
            "is_completed": true
          }
        ]
      },
      {
        "session_id": "demo_session_5",
        "goal": "Study Session Day 6",
        "status": "Finished",
        "start_time": "2025-06-23T00:01:45.287448",
        "end_time": "2025-06-23T02:16:45.287448",
        "rank": "A",
        "duration_seconds": 8100.0,
        "linked_quests_data": [
          {
            "quest_id": "quest_fbf73d96-abbb-48a1-ac75-027fb56eb5b4",
            "description": "Task 1 for Day 6",
            "difficulty": 3,
            "is_completed": true
          },
          {
            "quest_id": "quest_9ad0b424-36d8-4891-8392-463966f6c4af",
            "description": "Task 2 for Day 6",
            "difficulty": 1,
            "is_completed": false
          },
          {
            "quest_id": "quest_7fb0391a-85b0-4410-b19a-203452475406",
            "description": "Task 3 for Day 6",
            "difficulty": 1,
            "is_completed": true
          },
          {
            "quest_id": "quest_83739b10-cf4e-4d21-8941-3c2a35e1c612",
            "description": "Task 4 for Day 6",
            "difficulty": 3,
            "is_completed": true
          }
        ]
      },
      {
        "session_id": "demo_session_6",
        "goal": "Study Session Day 7",
        "status": "Finished",
        "start_time": "2025-06-24T00:01:45.287448",
        "end_time": "2025-06-24T02:20:45.287448",
        "rank": "S",
        "duration_seconds": 8340.0,
        "linked_quests_data": [
          {
            "quest_id": "quest_bdda5ac6-e472-4dac-bd6f-29c2a5de7bfd",
            "description": "Task 1 for Day 7",
            "difficulty": 1,
            "is_completed": false
          },
          {
            "quest_id": "quest_ed9b4d9a-b074-4226-9862-555ccbed2a41",
            "description": "Task 2 for Day 7",
            "difficulty": 1,
            "is_completed": true
          },
          {
            "quest_id": "quest_2a119ca2-6459-42f5-acd0-caedfa739d11",
            "description": "Task 3 for Day 7",
            "difficulty": 3,
            "is_completed": false
          }
        ]
      },
      {
        "session_id": "demo_session_7",
        "goal": "Study Session Day 8",
        "status": "Finished",
        "start_time": "2025-06-25T00:01:45.287448",
        "end_time": "2025-06-25T02:36:45.287448",
        "rank": "S",
        "duration_seconds": 9300.0,
        "linked_quests_data": [
          {
            "quest_id": "quest_ccce374e-889e-46ff-a694-ee87c98362e2",
            "description": "Task 1 for Day 8",
            "difficulty": 2,
            "is_completed": false
          },
          {
            "quest_id": "quest_588c0699-a30e-4726-9037-d2571066cb2b",
            "description": "Task 2 for Day 8",
            "difficulty": 1,
            "is_completed": true
          },
          {
            "quest_id": "quest_e32fb651-3ea6-46fc-8174-5a73ae1681b1",
            "description": "Task 3 for Day 8",
            "difficulty": 3,
            "is_completed": false
          }
        ]
      },
      {
        "session_id": "demo_session_8",
        "goal": "Study Session Day 9",
        "status": "Finished",
        "start_time": "2025-06-26T00:01:45.287448",
        "end_time": "2025-06-26T02:12:45.287448",
        "rank": "C",
        "duration_seconds": 7860.0,
        "linked_quests_data": [
          {
            "quest_id": "quest_e1e5ec08-edc0-4760-8faf-cc4b1553f9fb",
            "description": "Task 1 for Day 9",
            "difficulty": 3,
            "is_completed": true
          },
          {
            "quest_id": "quest_c428a51e-5252-4ae2-9593-736c4d27745d",
            "description": "Task 2 for Day 9",
            "difficulty": 3,
            "is_completed": true
          },
          {
            "quest_id": "quest_fb530acc-da8d-4e3f-8f14-53c8181bc9b9",
            "description": "Task 3 for Day 9",
            "difficulty": 2,
            "is_completed": true
          },
          {
            "quest_id": "quest_25246ea7-c131-4cc0-bc09-86ad04dd80b5",
            "description": "Task 4 for Day 9",
            "difficulty": 1,
            "is_completed": true
          }
        ]
      },
      {
        "session_id": "demo_session_9",
        "goal": "Study Session Day 10",
        "status": "Finished",
        "start_time": "2025-06-27T00:01:45.287448",
        "end_time": "2025-06-27T02:26:45.287448",
        "rank": "C",
        "duration_seconds": 8700.0,
        "linked_quests_data": [
          {
            "quest_id": "quest_ab0f62f5-7962-42a4-a2ee-0297a6a8647d",
            "description": "Task 1 for Day 10",
            "difficulty": 3,
            "is_completed": true
          },
          {
            "quest_id": "quest_d7c93f32-50e6-4dfe-98c5-71a99414586e",
            "description": "Task 2 for Day 10",
            "difficulty": 3,
            "is_completed": true
          }
        ]
      }
    ],
    "aggregated_stats": {
      "total_study_seconds": 88140.0,
      "total_study_hours": 24.483333333333334,
      "total_sessions": 10,
      "rank_counts": {
        "S": 2,
        "A": 3,
        "B": 0,
        "C": 5,
        "F": 0
      },
      "average_session_duration_minutes": 146.9,
      "average_rank_score": 3.2,
      "quests_completed": 6,
      "quest_completion_rate": 75.0
    },
    "focus_streak": 5
  },
  "sessions": [],
  "quest_system": {
    "active_quests": [
      {
        "quest_id": "quest_755f3691-b376-4077-9789-861d7e20e2f9",
        "description": "Demo Quest 1: Study Session Task",
        "difficulty": 2,
        "is_completed": true
      },
      {
        "quest_id": "quest_6f8d5616-e9f7-4c3f-b635-47e1637757c6",
        "description": "Demo Quest 2: Study Session Task",
        "difficulty": 5,
        "is_completed": true
      },
      {
        "quest_id": "quest_f91ad7ea-9826-4fbb-aa4f-869d1f8b5636",
        "description": "Demo Quest 3: Study Session Task",
        "difficulty": 1,
        "is_completed": true
      },
      {
        "quest_id": "quest_1782a4c3-d78a-4fa8-a6a3-ef6cf7321857",
        "description": "Demo Quest 4: Study Session Task",
        "difficulty": 4,
        "is_completed": true
      },
      {
        "quest_id": "quest_d56bb715-cb45-480c-8d7b-3b24566a9506",
        "description": "Demo Quest 5: Study Session Task",
        "difficulty": 4,
        "is_completed": true
      },
      {
        "quest_id": "quest_558d0389-f7ae-4736-9e02-e35f68ae6c42",
        "description": "Demo Quest 6: Study Session Task",
        "difficulty": 2,
        "is_completed": true
      },
      {
        "quest_id": "quest_4a4a55c7-b034-4dc2-87ad-3da026ec5f66",
        "description": "Demo Quest 7: Study Session Task",
        "difficulty": 3,
        "is_completed": false
      },
      {
        "quest_id": "quest_1ed27d19-876f-457c-94f8-c6a35acde675",
        "description": "Demo Quest 8: Study Session Task",
        "difficulty": 3,
        "is_completed": false
      }
    ]
  },
  "save_timestamp": "2025-06-27T10:02:26.647931",
  "version": "1.0"
}